android_setools-4.5.0.dev3.data/data/share/man/man1/apol.1
android_setools-4.5.0.dev3.data/data/share/man/man1/sechecker.1
android_setools-4.5.0.dev3.data/data/share/man/man1/sediff.1
android_setools-4.5.0.dev3.data/data/share/man/man1/sedta.1
android_setools-4.5.0.dev3.data/data/share/man/man1/seinfo.1
android_setools-4.5.0.dev3.data/data/share/man/man1/seinfoflow.1
android_setools-4.5.0.dev3.data/data/share/man/man1/sesearch.1
android_setools-4.5.0.dev3.data/data/share/man/ru/man1/apol.1
android_setools-4.5.0.dev3.data/data/share/man/ru/man1/sediff.1
android_setools-4.5.0.dev3.data/data/share/man/ru/man1/sedta.1
android_setools-4.5.0.dev3.data/data/share/man/ru/man1/seinfo.1
android_setools-4.5.0.dev3.data/data/share/man/ru/man1/seinfoflow.1
android_setools-4.5.0.dev3.data/data/share/man/ru/man1/sesearch.1
android_setools-4.5.0.dev3.data/scripts/apol
android_setools-4.5.0.dev3.data/scripts/sechecker
android_setools-4.5.0.dev3.data/scripts/sediff
android_setools-4.5.0.dev3.data/scripts/sedta
android_setools-4.5.0.dev3.data/scripts/seinfo
android_setools-4.5.0.dev3.data/scripts/seinfoflow
android_setools-4.5.0.dev3.data/scripts/sesearch
setools/__init__.py
setools/_monkeypatch.py
setools/boolquery.py
setools/boundsquery.py
setools/categoryquery.py
setools/commonquery.py
setools/constraintquery.py
setools/defaultquery.py
setools/descriptors.py
setools/devicetreeconquery.py
setools/dta.py
setools/exception.py
setools/fsusequery.py
setools/genfsconquery.py
setools/ibendportconquery.py
setools/ibpkeyconquery.py
setools/infoflow.py
setools/initsidquery.py
setools/iomemconquery.py
setools/ioportconquery.py
setools/mixins.py
setools/mlsrulequery.py
setools/netifconquery.py
setools/nodeconquery.py
setools/objclassquery.py
setools/pcideviceconquery.py
setools/perm_map
setools/permmap.py
setools/pirqconquery.py
setools/polcapquery.py
setools/policyrep.cpython-311-x86_64-linux-gnu.so
setools/policyrep.pyi
setools/portconquery.py
setools/py.typed
setools/query.py
android_setools-4.5.0.dev3.dist-info/COPYING
android_setools-4.5.0.dev3.dist-info/COPYING.GPL
android_setools-4.5.0.dev3.dist-info/COPYING.LGPL
android_setools-4.5.0.dev3.dist-info/METADATA
android_setools-4.5.0.dev3.dist-info/WHEEL
android_setools-4.5.0.dev3.dist-info/top_level.txt
android_setools-4.5.0.dev3.dist-info/RECORD
